trial1/__init__.py
trial1-1.0.1.dist-info/METADATA
trial1-1.0.1.dist-info/WHEEL
trial1-1.0.1.dist-info/top_level.txt
trial1-1.0.1.dist-info/RECORD
